glibs_ndb-3.0.0-py3.10-nspkg.pth
glibs/ndb/ProtocolBuffer.py
glibs/ndb/__init__.py
glibs/ndb/compat.py
glibs/ndb/entity_pb.py
glibs/ndb/ndb.py
glibs_ndb-3.0.0.dist-info/METADATA
glibs_ndb-3.0.0.dist-info/WHEEL
glibs_ndb-3.0.0.dist-info/namespace_packages.txt
glibs_ndb-3.0.0.dist-info/top_level.txt
glibs_ndb-3.0.0.dist-info/RECORD
