Metadata-Version: 2.1
Name: glibs-ndb
Version: 3.0.0
Summary: UNKNOWN
Home-page: UNKNOWN
License: UNKNOWN
Platform: UNKNOWN
Requires-Python: !=3.0.*,!=3.1.*,!=3.2.*,!=3.3.*,!=3.4.*,!=3.5.*,!=3.6.*,!=3.7.*,>=2.7
Requires-Dist: six (<2,>=1.16.0)
